README.md
setup.cfg
setup.py
DreamDiff/DreamDiff.py
DreamDiff/DreamOptimize.py
DreamDiff/__init__.py
DreamDiff/animation_demos.py
DreamDiff/demo1.py
DreamDiff/demo2.py
DreamDiff/demo3.py
DreamDiff/demo4.py
DreamDiff/test_DreamDiff.py
DreamDiff/test_DreamOptimize.py
DreamDiff.egg-info/PKG-INFO
DreamDiff.egg-info/SOURCES.txt
DreamDiff.egg-info/dependency_links.txt
DreamDiff.egg-info/top_level.txt