Metadata-Version: 2.1
Name: DreamDiff
Version: 1.0.1
Summary: A Python package for automatic differentiation, root-finding, optimization, and interpolation
Home-page: https://github.com/autodiffdreamteam/cs107-FinalProject
Author: Blake Bullwinkel, Aditya Kumar, Carlos Robles
Author-email: jbullwinkel@fas.harvard.edu, adityakumar@g.harvard.edu, carlosrobles@college.harvard.edu
License: UNKNOWN
Platform: UNKNOWN
Classifier: Programming Language :: Python :: 3
Classifier: License :: OSI Approved :: MIT License
Classifier: Operating System :: OS Independent
Requires-Python: >=3.6
